LICENSE
MANIFEST.in
README.md
runtests.py
setup.py
requirements/install.txt
requirements/tests.txt
wagtailsystemtext/__init__.py
wagtailsystemtext/admin.py
wagtailsystemtext/app_settings.py
wagtailsystemtext/apps.py
wagtailsystemtext/middlewares.py
wagtailsystemtext/models.py
wagtailsystemtext/tests.py
wagtailsystemtext/utils.py
wagtailsystemtext/views.py
wagtailsystemtext/wagtail_hooks.py
wagtailsystemtext.egg-info/PKG-INFO
wagtailsystemtext.egg-info/SOURCES.txt
wagtailsystemtext.egg-info/dependency_links.txt
wagtailsystemtext.egg-info/not-zip-safe
wagtailsystemtext.egg-info/requires.txt
wagtailsystemtext.egg-info/top_level.txt
wagtailsystemtext/management/__init__.py
wagtailsystemtext/management/commands/__init__.py
wagtailsystemtext/management/commands/add_systemtext.py
wagtailsystemtext/management/commands/delete_systemtext.py
wagtailsystemtext/management/commands/find_and_add_systemtext.py
wagtailsystemtext/management/commands/list_systemtext.py
wagtailsystemtext/management/commands/sync_systemtext.py
wagtailsystemtext/migrations/0001_initial.py
wagtailsystemtext/migrations/__init__.py
wagtailsystemtext/templatetags/__init__.py
wagtailsystemtext/templatetags/systemtext.py